[{"intent":"distance_today","utterance":"how much distance did I cover today"},
{"intent":"distance_today","utterance":"today walking distance kya hai"},
{"intent":"distance_today","utterance":"show my today's distance"},
{"intent":"distance_today","utterance":"distance covered today"},
{"intent":"distance_today","utterance":"aaj maine kitna distance walk kiya"},
{"intent":"distance_today","utterance":"today total running distance"},
{"intent":"distance_today","utterance":"my distance today report"},
{"intent":"distance_today","utterance":"how far did I walk today"},
{"intent":"distance_today","utterance":"distance travelled today in km"},
{"intent":"distance_today","utterance":"show today's step distance"},
{"intent":"distance_today","utterance":"today ka walking distance batao"},
{"intent":"distance_today","utterance":"distance today summary please"},
{"intent":"distance_today","utterance":"what is my total distance for today"},
{"intent":"distance_today","utterance":"today distance covered in meters"},
{"intent":"distance_today","utterance":"running distance today kya hai"},
{"intent":"distance_today","utterance":"how many km did I run today"},
{"intent":"distance_today","utterance":"show me today's travel distance"},
{"intent":"distance_today","utterance":"aaj ka distance report dikhao"},
{"intent":"distance_today","utterance":"distance walked today till now"},
{"intent":"distance_today","utterance":"today total movement distance"},
{"intent":"distance_today","utterance":"kitna chal chuka hu aaj"},
{"intent":"distance_today","utterance":"distance covered so far today"},
{"intent":"distance_today","utterance":"track today's walking distance"},
{"intent":"distance_today","utterance":"daily distance update chahiye"},
{"intent":"distance_today","utterance":"distance summary for today please"},
{"intent":"distance_today","utterance":"how many kilometers I walked today"},
{"intent":"distance_today","utterance":"today walking km report"},
{"intent":"distance_today","utterance":"distance travelled so far today"},
{"intent":"distance_today","utterance":"show me km covered today"},
{"intent":"distance_today","utterance":"distance report of today's activity"},
{"intent":"distance_today","utterance":"today running + walking distance total"},
{"intent":"distance_today","utterance":"aaj kitne km complete hue"},
{"intent":"distance_today","utterance":"distance ka full report for today"},
{"intent":"distance_today","utterance":"what's my distance walked today in app"},
{"intent":"distance_today","utterance":"today steps to distance conversion report"},
{"intent":"distance_today","utterance":"distance covered in today's workout"},
{"intent":"distance_today","utterance":"total walking running distance today"},
{"intent":"distance_today","utterance":"show distance stats for today"},
{"intent":"distance_today","utterance":"aaj ka total distance kitna hai"},
{"intent":"distance_today","utterance":"distance traveled today check karo"},
{"intent":"distance_today","utterance":"today walking distance tracker result"},
{"intent":"distance_today","utterance":"distance covered till now today in km"},
{"intent":"distance_today","utterance":"show my fitness distance today"},
{"intent":"distance_today","utterance":"today activity distance report batao"},
{"intent":"distance_today","utterance":"distance walked today in simple report"},
{"intent":"distance_today","utterance":"how much I moved today in km"},
{"intent":"distance_today","utterance":"today distance summary full details"},
{"intent":"distance_today","utterance":"distance update for today's activity"},
{"intent":"distance_today","utterance":"track my total distance today"},
{"intent":"distance_today","utterance":"distance walked and run today report"},
{"intent":"distance_today","utterance":"today total km covered in fitness app"},
{"intent":"distance_today","utterance":"more distance today queries"},
{"intent":"distance_today","utterance":"give more examples for today's distance check"},
{"intent":"distance_today","utterance":"show extra ways to ask distance covered today"},
{"intent":"distance_today","utterance":"aaj ka distance puchne ke aur tareeke batao"},
{"intent":"distance_today","utterance":"how to ask more about today's distance in app"},
{"intent":"distance_today","utterance":"more phrases for distance today intent"},
{"intent":"distance_today","utterance":"different ways to say distance covered today"},
{"intent":"distance_today","utterance":"more user queries for walking distance today"},
{"intent":"distance_today","utterance":"extra variations for today's distance report"},
{"intent":"distance_today","utterance":"additional sentences for distance today intent"},
{"intent":"distance_today","utterance":"other ways to ask how far I walked today"},
{"intent":"distance_today","utterance":"more natural voice queries for today distance"},
{"intent":"distance_today","utterance":"aaj kitna chala hu aur kya kya bol sakte hai"},
{"intent":"distance_today","utterance":"more conversational queries for distance tracking today"},
{"intent":"distance_today","utterance":"different voice commands for today's distance check"},
{"intent":"distance_today","utterance":"more casual Hindi English queries for distance today"},
{"intent":"distance_today","utterance":"additional user inputs for fitness distance today"},
{"intent":"distance_today","utterance":"more examples for walking running distance today"},
{"intent":"distance_today","utterance":"extra voice search queries for distance covered today"},
{"intent":"distance_today","utterance":"more dataset entries for distance today intent"},
{"intent":"distance_today","utterance":"various ways to ask today's fitness distance"},
{"intent":"distance_today","utterance":"more utterances for distance tracking intent today"},
{"intent":"distance_today","utterance":"extra variations for how far did I go today"},
{"intent":"distance_today","utterance":"more ways users ask total km today"},
{"intent":"distance_today","utterance":"different phrasings for today's walking stats"},
{"intent":"distance_today","utterance":"more training examples for distance_today intent"},
{"intent":"distance_today","utterance":"additional voice queries for today's km report"},
{"intent":"distance_today","utterance":"more conversational inputs for distance report today"},
{"intent":"distance_today","utterance":"extra Hindi English mixed queries for distance today"},
{"intent":"distance_today","utterance":"more natural speech patterns for walking distance today"},
{"intent":"distance_today","utterance":"how much did I walk today in km"},
{"intent":"distance_today","utterance":"show my total walking distance for today"},
{"intent":"distance_today","utterance":"aaj ka total distance kitna hua hai"},
{"intent":"distance_today","utterance":"distance covered till now today report batao"},
{"intent":"distance_today","utterance":"today running aur walking distance total"},
{"intent":"distance_today","utterance":"how far have I moved today in km"},
{"intent":"distance_today","utterance":"daily distance summary for today please"},
{"intent":"distance_today","utterance":"show complete distance report of today"},
{"intent":"distance_today","utterance":"kitna km cover kiya aaj maine"},
{"intent":"distance_today","utterance":"today distance tracking full detail"},
{"intent":"distance_today","utterance":"distance walked today overall summary"},
{"intent":"distance_today","utterance":"show me today's total km covered"},
{"intent":"distance_today","utterance":"what is my walking distance so far today"},
{"intent":"distance_today","utterance":"distance report for today's activity in app"},
{"intent":"distance_today","utterance":"aaj ke steps ka distance conversion batao"},
{"intent":"distance_today","utterance":"today movement distance summary please"},
{"intent":"distance_today","utterance":"how many kilometers covered in today's workout"},
{"intent":"distance_today","utterance":"distance traveled today till now"},
{"intent":"distance_today","utterance":"show today's fitness distance stats"},
{"intent":"distance_today","utterance":"complete walking distance update for today"},
{"intent":"distance_today","utterance":"how much distance did I cover in today's run"},
{"intent":"distance_today","utterance":"today walking + running distance combined"},
{"intent":"distance_today","utterance":"distance summary of today's exercise"},
{"intent":"distance_today","utterance":"aaj ka fitness distance report dikhao"},
{"intent":"distance_today","utterance":"track my distance covered today so far"},
{"intent":"distance_today","utterance":"show km walked today in simple format"},
{"intent":"distance_today","utterance":"today total activity distance in km please"},
{"intent":"distance_today","utterance":"distance covered in today's health tracking"},
{"intent":"distance_today","utterance":"how far did I go today in total"},
{"intent":"distance_today","utterance":"today distance summary from fitness tracker"},
{"intent":"distance_today","utterance":"how much distance did I cover today"},
{"intent":"distance_today","utterance":"show my distance today"},
{"intent":"distance_today","utterance":"today walking distance kya hai"},
{"intent":"distance_today","utterance":"distance covered today"},
{"intent":"distance_today","utterance":"aaj kitna chala hu"},
{"intent":"distance_today","utterance":"how far did I walk today"},
{"intent":"distance_today","utterance":"today total km walked"},
{"intent":"distance_today","utterance":"distance report for today"},
{"intent":"distance_today","utterance":"show today's distance summary"},
{"intent":"distance_today","utterance":"kitna distance cover kiya aaj"},
{"intent":"distance_today","utterance":"today running distance"},
{"intent":"distance_today","utterance":"today walking + running distance"},
{"intent":"distance_today","utterance":"distance tracked today"},
{"intent":"distance_today","utterance":"show me today's movement distance"},
{"intent":"distance_today","utterance":"how many km today"},
{"intent":"distance_today","utterance":"today distance in km"},
{"intent":"distance_today","utterance":"total distance so far today"},
{"intent":"distance_today","utterance":"distance covered so far today"},
{"intent":"distance_today","utterance":"aaj ka total distance batao"},
{"intent":"distance_today","utterance":"today activity distance report"},
{"intent":"distance_today","utterance":"show walking distance for today"},
{"intent":"distance_today","utterance":"how much I moved today"},
{"intent":"distance_today","utterance":"today fitness distance report"},
{"intent":"distance_today","utterance":"distance summary today please"},
{"intent":"distance_today","utterance":"aaj kitne km chale"},
{"intent":"distance_today","utterance":"how far have I gone today"},
{"intent":"distance_today","utterance":"today step distance"},
{"intent":"distance_today","utterance":"convert today's steps to distance"},
{"intent":"distance_today","utterance":"distance from today's steps"},
{"intent":"distance_today","utterance":"today workout distance"},
{"intent":"distance_today","utterance":"distance covered in workout today"},
{"intent":"distance_today","utterance":"show today's exercise distance"},
{"intent":"distance_today","utterance":"aaj exercise me kitna distance hua"},
{"intent":"distance_today","utterance":"today jogging distance"},
{"intent":"distance_today","utterance":"today run distance report"},
{"intent":"distance_today","utterance":"running + walking distance today"},
{"intent":"distance_today","utterance":"distance total today report"},
{"intent":"distance_today","utterance":"today travel distance in fitness app"},
{"intent":"distance_today","utterance":"distance check for today"},
{"intent":"distance_today","utterance":"show full distance report today"},
{"intent":"distance_today","utterance":"today distance tracker result"},
{"intent":"distance_today","utterance":"how much distance I walked today in km"},
{"intent":"distance_today","utterance":"today walking stats distance"},
{"intent":"distance_today","utterance":"distance covered till now today"},
{"intent":"distance_today","utterance":"today movement in km"},
{"intent":"distance_today","utterance":"show km covered today"},
{"intent":"distance_today","utterance":"today physical activity distance"},
{"intent":"distance_today","utterance":"distance report of today's activity"},
{"intent":"distance_today","utterance":"aaj ka fitness distance kitna hai"},
{"intent":"distance_today","utterance":"today walking tracking report"},
{"intent":"distance_today","utterance":"distance analysis for today"},
{"intent":"distance_today","utterance":"today distance update please"},
{"intent":"distance_today","utterance":"how far did I move today in km"},
{"intent":"distance_today","utterance":"today total walking distance check"},
{"intent":"distance_today","utterance":"distance covered in today's walk"},
{"intent":"distance_today","utterance":"today jogging + walking total distance"},
{"intent":"distance_today","utterance":"show my total movement today"},
{"intent":"distance_today","utterance":"today activity tracking distance"},
{"intent":"distance_today","utterance":"distance summary of today activity"},
{"intent":"distance_today","utterance":"aaj ka movement report batao"},
{"intent":"distance_today","utterance":"how much I walked or ran today"},
{"intent":"distance_today","utterance":"today full distance stats"},
{"intent":"distance_today","utterance":"distance dashboard for today"},
{"intent":"distance_today","utterance":"show today's fitness tracking distance"},
{"intent":"distance_today","utterance":"today distance analytics"},
{"intent":"distance_today","utterance":"how many kilometers I covered today"},
{"intent":"distance_today","utterance":"today total distance covered report"},
{"intent":"distance_today","utterance":"distance summary of walking today"},
{"intent":"distance_today","utterance":"today running stats distance"},
{"intent":"distance_today","utterance":"distance covered in steps today"},
{"intent":"distance_today","utterance":"today step based distance report"},
{"intent":"distance_today","utterance":"aaj ka step distance batao"},
{"intent":"distance_today","utterance":"distance converted from steps today"},
{"intent":"distance_today","utterance":"how far I walked based on steps today"},
{"intent":"distance_today","utterance":"today workout movement distance report"},
{"intent":"distance_today","utterance":"distance covered in fitness session today"},
{"intent":"distance_today","utterance":"show activity distance today"},
{"intent":"distance_today","utterance":"today health tracking distance"},
{"intent":"distance_today","utterance":"distance summary from health app today"},
{"intent":"distance_today","utterance":"today total km walked and run"},
{"intent":"distance_today","utterance":"how much distance in today's fitness tracking"},
{"intent":"distance_today","utterance":"distance report from today's workout"},
{"intent":"distance_today","utterance":"today complete movement distance"},
{"intent":"distance_today","utterance":"aaj ka total chalne ka distance"},
{"intent":"distance_today","utterance":"how far I moved in fitness app today"},
{"intent":"distance_today","utterance":"today walking distance full report"},
{"intent":"distance_today","utterance":"distance covered till now in today's activity"},
{"intent":"distance_today","utterance":"show today's total movement in km"},
{"intent":"distance_today","utterance":"today physical movement tracking report"},
{"intent":"distance_today","utterance":"distance stats for today's health tracking"},
{"intent":"distance_today","utterance":"how much I walked today overall"},
{"intent":"distance_today","utterance":"today fitness journey distance report"},
{"intent":"distance_today","utterance":"distance covered in today's step count"},
{"intent":"distance_today","utterance":"show me complete distance for today"},
{"intent":"distance_today","utterance":"today activity summary distance"},
{"intent":"distance_today","utterance":"distance update of today's fitness"},
{"intent":"distance_today","utterance":"how many km walked in total today"},
{"intent":"distance_today","utterance":"today movement summary in km"},
{"intent":"distance_today","utterance":"distance report full for today activity"},
{"intent":"distance_today","utterance":"how much distance did I cover today in km"},
{"intent":"distance_today","utterance":"show today's total walking distance in km"},
{"intent":"distance_today","utterance":"aaj maine total kitna distance cover kiya"},
{"intent":"distance_today","utterance":"today walking distance full report please"},
{"intent":"distance_today","utterance":"distance covered today till now in km"},
{"intent":"distance_today","utterance":"how far have I walked today total"},
{"intent":"distance_today","utterance":"today fitness app distance report"},
{"intent":"distance_today","utterance":"show me today's total movement distance"},
{"intent":"distance_today","utterance":"kitne km chale aaj overall"},
{"intent":"distance_today","utterance":"today running and walking combined distance"},
{"intent":"distance_today","utterance":"distance report for today's full activity"},
{"intent":"distance_today","utterance":"aaj ka complete distance tracking report"},
{"intent":"distance_today","utterance":"how many km I moved today total"},
{"intent":"distance_today","utterance":"today step based distance summary"},
{"intent":"distance_today","utterance":"distance converted from today's steps report"},
{"intent":"distance_today","utterance":"show today's fitness distance analytics"},
{"intent":"distance_today","utterance":"today workout total distance covered"},
{"intent":"distance_today","utterance":"distance covered during exercise today"},
{"intent":"distance_today","utterance":"how far did I go in today's workout"},
{"intent":"distance_today","utterance":"today jogging distance in km report"},
{"intent":"distance_today","utterance":"today walking + running distance total report"},
{"intent":"distance_today","utterance":"distance summary of today's fitness activity"},
{"intent":"distance_today","utterance":"aaj ka fitness tracking distance batao"},
{"intent":"distance_today","utterance":"today activity distance dashboard"},
{"intent":"distance_today","utterance":"show complete distance stats for today"},
{"intent":"distance_today","utterance":"how much distance I walked so far today"},
{"intent":"distance_today","utterance":"today total movement in kilometers"},
{"intent":"distance_today","utterance":"distance report from health tracker today"},
{"intent":"distance_today","utterance":"show today's walking stats in km"},
{"intent":"distance_today","utterance":"today physical activity distance summary"},
{"intent":"distance_today","utterance":"distance covered in today's health tracking app"},
{"intent":"distance_today","utterance":"how far I moved in km today report"},
{"intent":"distance_today","utterance":"today fitness journey distance analytics"},
{"intent":"distance_today","utterance":"distance tracking report for today full details"},
{"intent":"distance_today","utterance":"aaj ka total chalne ka distance report"},
{"intent":"distance_today","utterance":"how many kilometers walked in today's session"},
{"intent":"distance_today","utterance":"today movement distance check karo"},
{"intent":"distance_today","utterance":"distance summary from today's steps and run"},
{"intent":"distance_today","utterance":"show me complete movement distance today"},
{"intent":"distance_today","utterance":"today health app distance summary"},
{"intent":"distance_today","utterance":"distance covered in today's fitness routine"},
{"intent":"distance_today","utterance":"how much distance I covered in today's run"},
{"intent":"distance_today","utterance":"today walking distance analytics report"},
{"intent":"distance_today","utterance":"distance covered till now in today's workout session"},
{"intent":"distance_today","utterance":"show today's total km walked and run"},
{"intent":"distance_today","utterance":"today step count to distance conversion report"},
{"intent":"distance_today","utterance":"distance report for today's walking exercise"},
{"intent":"distance_today","utterance":"how far did I travel today in fitness app"},
{"intent":"distance_today","utterance":"today full distance activity summary"},
{"intent":"distance_today","utterance":"distance analysis of today's movement"},
{"intent":"distance_today","utterance":"aaj ka complete fitness distance report batao"},
{"intent":"distance_today","utterance":"today workout and walk distance total"},
{"intent":"distance_today","utterance":"distance covered in today's health and fitness tracking"},
{"intent":"distance_today","utterance":"show me today's movement stats in km"},
{"intent":"distance_today","utterance":"today total distance walked report please"},
{"intent":"distance_today","utterance":"how much I moved today in total km"},
{"intent":"distance_today","utterance":"distance dashboard report for today's activity"},
{"intent":"distance_today","utterance":"today fitness tracker distance full report"},
{"intent":"distance_today","utterance":"distance covered in today's steps and workouts"},
{"intent":"distance_today","utterance":"show today's complete activity distance in km"},
{"intent":"distance_today","utterance":"today walking + exercise distance summary"},
{"intent":"distance_today","utterance":"how many km I covered in today's fitness journey"},
{"intent":"distance_today","utterance":"today total physical activity distance report"},
{"intent":"distance_today","utterance":"distance tracking summary for today in app"},
{"intent":"distance_today","utterance":"aaj ka total movement aur distance batao"},
{"intent":"distance_today","utterance":"today full health tracking distance report"},
{"intent":"distance_today","utterance":"distance covered in today's fitness session summary"},
{"intent":"distance_today","utterance":"show me full distance analytics of today"},
{"intent":"distance_today","utterance":"today walking running full distance breakdown"},
{"intent":"distance_today","utterance":"distance report for today's complete fitness activity"},
{"intent":"distance_today","utterance":"how much distance I achieved today in km"},
{"intent":"distance_today","utterance":"today total km covered in health app"},
{"intent":"distance_today","utterance":"distance summary of today's step tracking"},
{"intent":"distance_today","utterance":"show today's complete walking distance analytics"},
{"intent":"distance_today","utterance":"today movement and exercise distance report"},
{"intent":"distance_today","utterance":"distance covered in today's full workout session"},
{"intent":"distance_today","utterance":"how far I went today in total km report"},
{"intent":"distance_today","utterance":"today fitness distance summary in detail"},
{"intent":"distance_today","utterance":"distance tracking result for today's activity"},
{"intent":"distance_today","utterance":"aaj ka full movement distance analytics report"},
{"intent":"distance_today","utterance":"today walking and running total km report"},
{"intent":"distance_today","utterance":"distance covered in today's health tracking session"},
{"intent":"distance_today","utterance":"show me complete today's distance report in km"},
{"intent":"distance_today","utterance":"today fitness app total distance analytics"},
{"intent":"distance_today","utterance":"distance summary of today's complete workout"},
{"intent":"distance_today","utterance":"how much distance I walked and ran today total"},
{"intent":"distance_today","utterance":"today movement tracking full report in km"},
{"intent":"distance_today","utterance":"distance covered in today's full day activity"},
{"intent":"distance_today","utterance":"show today's total fitness distance breakdown"},
{"intent":"distance_today","utterance":"today health and workout distance report full"},
{"intent":"distance_today","utterance":"distance analytics for today's fitness journey"},
{"intent":"distance_today","utterance":"aaj ka total km aur movement report batao"},
{"intent":"distance_today","utterance":"today complete distance tracking summary report"},
{"intent":"distance_today","utterance":"aaj total kitna distance cover hua hai"},
{"intent":"distance_today","utterance":"today total distance kitna gaya walking me"},
{"intent":"distance_today","utterance":"how much distance covered overall today"},
{"intent":"distance_today","utterance":"show me full day distance report"},
{"intent":"distance_today","utterance":"distance today total including walk and run"},
{"intent":"distance_today","utterance":"aaj maine kitne km chale overall"},
{"intent":"distance_today","utterance":"today total km walked and jogged"},
{"intent":"distance_today","utterance":"how far did I move the whole day"},
{"intent":"distance_today","utterance":"complete distance summary for today please"},
{"intent":"distance_today","utterance":"today movement total distance batao"},
{"intent":"distance_today","utterance":"kitna chal chuka hu aaj total"},
{"intent":"distance_today","utterance":"today walking distance plus running distance total"},
{"intent":"distance_today","utterance":"distance covered today overall summary"},
{"intent":"distance_today","utterance":"show today's final distance in km"},
{"intent":"distance_today","utterance":"aaj ka total fitness distance report do"},
{"intent":"distance_today","utterance":"how many km total I did today"},
{"intent":"distance_today","utterance":"today full activity distance summary please"},
{"intent":"distance_today","utterance":"distance report for entire day today"},
{"intent":"distance_today","utterance":"aaj ka complete chalne ka data chahiye"},
{"intent":"distance_today","utterance":"today total movement stats in km batao"},
{"intent":"distance_today","utterance":"how much distance I covered from morning till now"},
{"intent":"distance_today","utterance":"today overall walking running distance report"},
{"intent":"distance_today","utterance":"distance tracker full day result show karo"},
{"intent":"distance_today","utterance":"show me today's total movement in kilometers"},
{"intent":"distance_today","utterance":"aaj ka total distance health app me kitna hai"},
{"intent":"distance_today","utterance":"today complete fitness distance data please"},
{"intent":"distance_today","utterance":"distance covered from all activities today total"},
{"intent":"distance_today","utterance":"how far I walked in total today report"},
{"intent":"distance_today","utterance":"today overall km covered in all workouts"},
{"intent":"distance_today","utterance":"distance summary of full day activity today"},
{"intent":"distance_today","utterance":"show complete today's walking and running distance"},
{"intent":"distance_today","utterance":"aaj ka full movement aur km report batao"},
{"intent":"distance_today","utterance":"today total steps converted to distance summary"},
{"intent":"distance_today","utterance":"distance tracking complete report for today"},
{"intent":"distance_today","utterance":"how many km I achieved in full day activity"},
{"intent":"distance_today","utterance":"today fitness journey total distance summary"},
{"intent":"distance_today","utterance":"distance report full day health tracking app"},
{"intent":"distance_today","utterance":"show today's movement total km breakdown"},
{"intent":"distance_today","utterance":"aaj ka walking running combined distance kitna hai"},
{"intent":"distance_today","utterance":"today complete distance from fitness tracker app"},
{"intent":"distance_today","utterance":"how much distance I covered in whole day workout"},
{"intent":"distance_today","utterance":"today total physical activity km report do"},
{"intent":"distance_today","utterance":"distance summary of today's entire fitness activity"},
{"intent":"distance_today","utterance":"show full day distance analytics in km"},
{"intent":"distance_today","utterance":"aaj ka health tracker distance final report"},
{"intent":"distance_today","utterance":"today complete walking jogging summary report"},
{"intent":"distance_today","utterance":"distance covered in all exercises today total"},
{"intent":"distance_today","utterance":"how far I moved in entire day fitness tracking"},
{"intent":"distance_today","utterance":"today full km report of all activities"},
{"intent":"distance_today","utterance":"distance analytics complete for today's workout"},
{"intent":"distance_today","utterance":"show me total distance from all today's steps"},
{"intent":"distance_today","utterance":"aaj ka final distance report in km batao"},
{"intent":"distance_today","utterance":"today overall movement fitness data summary"},
{"intent":"distance_today","utterance":"distance covered from morning to night today"},
{"intent":"distance_today","utterance":"how much total distance I did in fitness app today"},
{"intent":"distance_today","utterance":"today complete health and activity distance report"},
{"intent":"distance_today","utterance":"distance summary full day steps and workout"},
{"intent":"distance_today","utterance":"show today's total walking jogging km data"},
{"intent":"distance_today","utterance":"aaj ka total fitness movement report generate karo"},
{"intent":"distance_today","utterance":"today full activity km tracking result"},
{"intent":"distance_today","utterance":"distance report of entire day fitness usage"},
{"intent":"distance_today","utterance":"how many km total covered in today's activity"},
{"intent":"distance_today","utterance":"today movement complete analytics report show"},
{"intent":"distance_today","utterance":"distance covered in full day health tracking summary"},
{"intent":"distance_today","utterance":"show me today's final activity distance stats"},
{"intent":"distance_today","utterance":"aaj ka total walking running data summary"},
{"intent":"distance_today","utterance":"today fitness tracker full distance result"},
{"intent":"distance_today","utterance":"distance summary complete for today's workouts"},
{"intent":"distance_today","utterance":"how far I walked today full day report"},
{"intent":"distance_today","utterance":"today total km from all fitness activities"},
{"intent":"distance_today","utterance":"distance analytics for whole day activity report"},
{"intent":"distance_today","utterance":"show complete movement distance report today"},
{"intent":"distance_today","utterance":"aaj ka final health tracking km data"},
{"intent":"distance_today","utterance":"today total distance summary from fitness app"},
{"intent":"distance_today","utterance":"distance covered in complete day workout session"},
{"intent":"distance_today","utterance":"how much total movement I did today in km"},
{"intent":"distance_today","utterance":"today full day walking running stats report"},
{"intent":"distance_today","utterance":"distance report complete health and fitness summary"},
{"intent":"distance_today","utterance":"show today's total activity km breakdown report"},
{"intent":"distance_today","utterance":"aaj ka full distance tracking final output"},
{"intent":"distance_today","utterance":"today complete movement and workout distance data"},
{"intent":"distance_today","utterance":"distance summary of entire fitness day report"},
{"intent":"distance_today","utterance":"how many km I moved in total whole day today"},
{"intent":"distance_today","utterance":"today full fitness distance analytics report show"},
{"intent":"distance_today","utterance":"distance covered across all activities in one day"},
{"intent":"distance_today","utterance":"show me complete daily distance tracking result"},
{"intent":"distance_today","utterance":"aaj ka overall km aur activity summary batao"},
{"intent":"distance_today","utterance":"today full health dashboard distance report"},
{"intent":"distance_today","utterance":"distance analytics for full day fitness tracking"},
{"intent":"distance_today","utterance":"how far I went in today's complete fitness session"},
{"intent":"distance_today","utterance":"today total walking jogging running distance summary"},
{"intent":"distance_today","utterance":"aaj ka total distance kitna bana"},
{"intent":"distance_today","utterance":"today overall kitne km chale hain"},
{"intent":"distance_today","utterance":"how much total distance today in km"},
{"intent":"distance_today","utterance":"show today's full distance data quickly"},
{"intent":"distance_today","utterance":"distance total aaj ka batao fast"},
{"intent":"distance_today","utterance":"kitna distance cover kiya aaj overall"},
{"intent":"distance_today","utterance":"today total walking running combined km"},
{"intent":"distance_today","utterance":"how far did I go today total report"},
{"intent":"distance_today","utterance":"aaj ka complete movement distance kitna hai"},
{"intent":"distance_today","utterance":"today full day km summary show"},
{"intent":"distance_today","utterance":"distance report aaj ka full batao"},
{"intent":"distance_today","utterance":"how many km covered overall today fitness"},
{"intent":"distance_today","utterance":"today movement total distance check"},
{"intent":"distance_today","utterance":"aaj kitna chala hu total km me"},
{"intent":"distance_today","utterance":"today full activity distance kitna hua"},
{"intent":"distance_today","utterance":"show me total km walked today now"},
{"intent":"distance_today","utterance":"distance today full summary please show"},
{"intent":"distance_today","utterance":"how far I moved today overall fitness"},
{"intent":"distance_today","utterance":"aaj ka walking running total distance"},
{"intent":"distance_today","utterance":"today complete km report chahiye"},
{"intent":"distance_today","utterance":"distance covered today in simple report"},
{"intent":"distance_today","utterance":"show today's total fitness distance result"},
{"intent":"distance_today","utterance":"aaj ka movement data kitna hai km me"},
{"intent":"distance_today","utterance":"today overall exercise distance summary"},
{"intent":"distance_today","utterance":"how much distance I achieved today total"},
{"intent":"distance_today","utterance":"distance aaj ka final result batao"},
{"intent":"distance_today","utterance":"today full walking jogging distance report"},
{"intent":"distance_today","utterance":"kitne km chale aaj poore din me"},
{"intent":"distance_today","utterance":"today total movement in km show karo"},
{"intent":"distance_today","utterance":"distance report full day aaj ka"},
{"intent":"distance_today","utterance":"how far I walked today simple answer"},
{"intent":"distance_today","utterance":"aaj ka total health tracking distance"},
{"intent":"distance_today","utterance":"today fitness app total km result"},
{"intent":"distance_today","utterance":"distance complete today summary short"},
{"intent":"distance_today","utterance":"show me today's final km value"},
{"intent":"distance_today","utterance":"aaj kitna walk aur run kiya total"},
{"intent":"distance_today","utterance":"today total distance combined activities"},
{"intent":"distance_today","utterance":"how much I moved in km today overall"},
{"intent":"distance_today","utterance":"distance today full breakdown show"},
{"intent":"distance_today","utterance":"aaj ka complete fitness distance data"},
{"intent":"distance_today","utterance":"today walking running total report"},
{"intent":"distance_today","utterance":"show full day movement km summary"},
{"intent":"distance_today","utterance":"distance covered in whole day today result"},
{"intent":"distance_today","utterance":"how many km I walked today total check"},
{"intent":"distance_today","utterance":"aaj ka final movement report do"},
{"intent":"distance_today","utterance":"today overall health distance tracking"},
{"intent":"distance_today","utterance":"distance summary for today in km format"},
{"intent":"distance_today","utterance":"show today's total activity distance"},
{"intent":"distance_today","utterance":"aaj ka full workout distance kitna hai"},
{"intent":"distance_today","utterance":"today complete movement tracking result"},
{"intent":"distance_today","utterance":"how far I traveled today total fitness"},
{"intent":"distance_today","utterance":"distance report today overall activity"},
{"intent":"distance_today","utterance":"aaj ka walking data total km me batao"},
{"intent":"distance_today","utterance":"today full fitness journey distance"},
{"intent":"distance_today","utterance":"show me total distance of today now"},
{"intent":"distance_today","utterance":"distance covered in today's full session"},
{"intent":"distance_today","utterance":"how much km I did in whole day fitness"},
{"intent":"distance_today","utterance":"today total steps to km report"},
{"intent":"distance_today","utterance":"aaj ka complete steps distance summary"},
{"intent":"distance_today","utterance":"today full movement report in simple words"},
{"intent":"distance_today","utterance":"distance aaj ka overall fitness result"},
{"intent":"distance_today","utterance":"show today's total km walking running"},
{"intent":"distance_today","utterance":"aaj kitna total distance cover hua hai"},
{"intent":"distance_today","utterance":"today overall fitness km summary"},
{"intent":"distance_today","utterance":"how far I moved in total today report"},
{"intent":"distance_today","utterance":"distance today full health summary"},
{"intent":"distance_today","utterance":"aaj ka final total km tracking result"},
{"intent":"distance_today","utterance":"today complete activity distance check"},
{"intent":"distance_today","utterance":"show full day km fitness report"},
{"intent":"distance_today","utterance":"distance covered today overall simple"},
{"intent":"distance_today","utterance":"how much total walking done today"},
{"intent":"distance_today","utterance":"today full day fitness distance value"},
{"intent":"distance_today","utterance":"aaj ka movement complete report batao"},
{"intent":"distance_today","utterance":"today total distance in health app"},
{"intent":"distance_today","utterance":"distance summary aaj ka full data"},
{"intent":"distance_today","utterance":"show me complete km report today"},
{"intent":"distance_today","utterance":"aaj ka walking running final distance"},
{"intent":"distance_today","utterance":"today overall movement summary report"},
{"intent":"distance_today","utterance":"how far I walked and ran today total"},
{"intent":"distance_today","utterance":"distance covered full day report today"},
{"intent":"distance_today","utterance":"aaj ka fitness tracking km batao"},
{"intent":"distance_today","utterance":"today full activity km output"},
{"intent":"distance_today","utterance":"show today's total movement report simple"},
{"intent":"distance_today","utterance":"distance today complete tracking result"},
{"intent":"distance_today","utterance":"aaj ka final health report distance"},
{"intent":"distance_today","utterance":"today total km fitness summary check"},
{"intent":"distance_today","utterance":"how many km total activity today"},
{"intent":"distance_today","utterance":"distance report full today in km"},
{"intent":"distance_today","utterance":"aaj ka overall walking running stats"},
{"intent":"distance_today","utterance":"today full distance analytics simple"},
{"intent":"distance_today","utterance":"show complete today's movement km result"},
{"intent":"distance_today","utterance":"distance covered today final summary"},
{"intent":"distance_today","utterance":"aaj total kitna km chala hu simple batao"},
{"intent":"distance_today","utterance":"today kitna distance hua walking me overall"},
{"intent":"distance_today","utterance":"how much km I walked today exactly"},
{"intent":"distance_today","utterance":"show today's distance in km quick"},
{"intent":"distance_today","utterance":"aaj ka distance fast batao"},
{"intent":"distance_today","utterance":"today total km walking and running kitna"},
{"intent":"distance_today","utterance":"how far I walked today simple answer"},
{"intent":"distance_today","utterance":"aaj kitne km complete hue hain"},
{"intent":"distance_today","utterance":"today full distance report short form"},
{"intent":"distance_today","utterance":"distance today batao jaldi se"},
{"intent":"distance_today","utterance":"kitna chal chuka hu aaj total km"},
{"intent":"distance_today","utterance":"today movement total km value"},
{"intent":"distance_today","utterance":"how many km covered in today fitness"},
{"intent":"distance_today","utterance":"aaj ka walking total distance kya hai"},
{"intent":"distance_today","utterance":"today full activity km summary simple"},
{"intent":"distance_today","utterance":"show me total distance of today fast"},
{"intent":"distance_today","utterance":"distance aaj ka kitna hua hai"},
{"intent":"distance_today","utterance":"today total fitness km report quick"},
{"intent":"distance_today","utterance":"how far did I go today km wise"},
{"intent":"distance_today","utterance":"aaj ka complete distance batao short"},
{"intent":"distance_today","utterance":"today walking running total distance quick report"},
{"intent":"distance_today","utterance":"distance covered today overall simple answer"},
{"intent":"distance_today","utterance":"show today's km total immediately"},
{"intent":"distance_today","utterance":"aaj ka health tracking distance batao"},
{"intent":"distance_today","utterance":"today complete km walked summary short"},
{"intent":"distance_today","utterance":"how much I moved today in km simple"},
{"intent":"distance_today","utterance":"distance report aaj ka fast answer"},
{"intent":"distance_today","utterance":"today total walking distance kitna hai"},
{"intent":"distance_today","utterance":"aaj kitna run aur walk mila ke km hua"},
{"intent":"distance_today","utterance":"today full movement km quick result"},
{"intent":"distance_today","utterance":"show me today's distance quickly in numbers"},
{"intent":"distance_today","utterance":"distance today total simple report batao"},
{"intent":"distance_today","utterance":"how far I moved in km today fast"},
{"intent":"distance_today","utterance":"aaj ka final km kitna bana hai"},
{"intent":"distance_today","utterance":"today fitness app total distance quick view"},
{"intent":"distance_today","utterance":"distance covered today short answer do"},
{"intent":"distance_today","utterance":"show today's walking km fast result"},
{"intent":"distance_today","utterance":"aaj ka movement total km batao jaldi"},
{"intent":"distance_today","utterance":"today total distance easy summary"},
{"intent":"distance_today","utterance":"how many km I covered today overall quick"},
{"intent":"distance_today","utterance":"distance aaj ka simple number me batao"},
{"intent":"distance_today","utterance":"today full fitness km quick check"},
{"intent":"distance_today","utterance":"aaj ka walking running combined km fast"},
{"intent":"distance_today","utterance":"today total movement simple report now"},
{"intent":"distance_today","utterance":"distance today quick summary please"},
{"intent":"distance_today","utterance":"how far did I walk today total km short"},
{"intent":"distance_today","utterance":"aaj ka fitness distance fast view"},
{"intent":"distance_today","utterance":"today km total batao one line"},
{"intent":"distance_today","utterance":"distance covered today quick stats"},
{"intent":"distance_today","utterance":"show me today total km walking running fast"},
{"intent":"distance_today","utterance":"aaj kitna distance complete hua short answer"},
{"intent":"distance_today","utterance":"today overall km report simple form"},
{"intent":"distance_today","utterance":"how much distance I did today quick"},
{"intent":"distance_today","utterance":"distance aaj ka jaldi se batao"},
{"intent":"distance_today","utterance":"today full day km result short"},
{"intent":"distance_today","utterance":"aaj ka walking distance quick summary"},
{"intent":"distance_today","utterance":"today total fitness distance simple output"},
{"intent":"distance_today","utterance":"how far I went today km quick check"},
{"intent":"distance_today","utterance":"distance today full report one line"},
{"intent":"distance_today","utterance":"aaj ka total km fitness app me kitna hai"},
{"intent":"distance_today","utterance":"today movement km quick answer please"},
{"intent":"distance_today","utterance":"show today's total distance fast numbers"},
{"intent":"distance_today","utterance":"aaj ka complete km batao instantly"},
{"intent":"distance_today","utterance":"today walking running km quick info"},
{"intent":"distance_today","utterance":"distance covered today simple fast view"},
{"intent":"distance_today","utterance":"how many km I walked today quick result"},
{"intent":"distance_today","utterance":"aaj ka final distance short form batao"},
{"intent":"distance_today","utterance":"today total km easy answer please"},
{"intent":"distance_today","utterance":"distance today quick check report"},
{"intent":"distance_today","utterance":"show me today's km summary fast mode"},
{"intent":"distance_today","utterance":"aaj ka fitness total distance jaldi batao"},
{"intent":"distance_today","utterance":"today full distance quick info"},
{"intent":"distance_today","utterance":"how far I moved today simple km answer"},
{"intent":"distance_today","utterance":"distance aaj ka short and fast"},
{"intent":"distance_today","utterance":"today total walking running quick report"},
{"intent":"distance_today","utterance":"aaj kitna chal chuka hu fast batao"},
{"intent":"distance_today","utterance":"today km total quick check please"},
{"intent":"distance_today","utterance":"distance covered today easy quick summary"},
{"intent":"distance_today","utterance":"how much I walked today short answer"},
{"intent":"distance_today","utterance":"aaj ka movement km fast result"},
{"intent":"distance_today","utterance":"today full fitness distance quick output"},
{"intent":"distance_today","utterance":"distance today simple fast report"},
{"intent":"distance_today","utterance":"show today's km quick view only"},
{"intent":"distance_today","utterance":"aaj ka total walking running fast answer"},
{"intent":"distance_today","utterance":"today distance complete short info"},
{"intent":"distance_today","utterance":"how far I went today simple fast km"},
{"intent":"distance_today","utterance":"distance aaj ka one line answer"},
{"intent":"distance_today","utterance":"today total km quick summary report"},
{"intent":"distance_today","utterance":"aaj ka final fitness distance fast output"},
{"intent":"distance_today","utterance":"today walking distance quick numbers"},
{"intent":"distance_today","utterance":"distance covered today instant result"},
{"intent":"distance_today","utterance":"how many km today total simple"},
{"intent":"distance_today","utterance":"aaj ka km batao fast mode"},
{"intent":"distance_today","utterance":"today full distance quick check summary"},
{"intent":"distance_today","utterance":"distance today short fast answer only"}]